pyShelly/__init__.py
pyShelly/base.py
pyShelly/block.py
pyShelly/cloud.py
pyShelly/coap.py
pyShelly/compat.py
pyShelly/const.py
pyShelly/debug.py
pyShelly/device.py
pyShelly/dimmer.py
pyShelly/firmware.py
pyShelly/light.py
pyShelly/loop.py
pyShelly/mdns.py
pyShelly/mqtt.py
pyShelly/mqtt_client.py
pyShelly/mqtt_server.py
pyShelly/powermeter.py
pyShelly/relay.py
pyShelly/roller.py
pyShelly/sensor.py
pyShelly/switch.py
pyShelly/trv.py
pyShelly/utils.py
pyShelly/ws_client.py
pyShelly-1.0.4.dist-info/LICENSE
pyShelly-1.0.4.dist-info/METADATA
pyShelly-1.0.4.dist-info/WHEEL
pyShelly-1.0.4.dist-info/top_level.txt
pyShelly-1.0.4.dist-info/RECORD
