Metadata-Version: 2.1
Name: pyShelly
Version: 1.0.4
Summary: Library for Shelly smart home devices
Home-page: https://github.com/StyraHem/pyShelly
Author: StyraHem / Tarra AB
Author-email: info@styrahem.se
License: MIT
Classifier: Programming Language :: Python :: 2.7
Classifier: Programming Language :: Python :: 3
Classifier: License :: OSI Approved :: MIT License
Classifier: Operating System :: OS Independent
License-File: LICENSE
Requires-Dist: zeroconf
Requires-Dist: websocket-client
